reward-0.0.4.dist-info/METADATA
reward-0.0.4.dist-info/RECORD
reward-0.0.4.dist-info/WHEEL
reward-0.0.4.dist-info/top_level.txt
torchrl/__init__.py
torchrl/agents/__init__.py
torchrl/agents/base_agent.py
torchrl/agents/pg_agent.py
torchrl/arch/__init__.py
torchrl/arch/a3c_arch.py
torchrl/arch/base_arch.py
torchrl/arch/ddpg_critic_arch.py
torchrl/arch/mlp_arch.py
torchrl/batchers/__init__.py
torchrl/batchers/base_batcher.py
torchrl/batchers/replay_batcher.py
torchrl/batchers/rollout_batcher.py
torchrl/batchers/transforms/__init__.py
torchrl/batchers/transforms/base_transform.py
torchrl/batchers/transforms/common_transforms.py
torchrl/batchers/transforms/reward_transforms.py
torchrl/batchers/transforms/state_transforms.py
torchrl/distributions/__init__.py
torchrl/distributions/base_dist.py
torchrl/distributions/categorical.py
torchrl/distributions/normal.py
torchrl/envs/__init__.py
torchrl/envs/atari_env.py
torchrl/envs/base_env.py
torchrl/envs/gym_env.py
torchrl/envs/osim_env.py
torchrl/envs/roboschool_env.py
torchrl/envs/wrappers/__init__.py
torchrl/envs/wrappers/atari_wrapper.py
torchrl/envs/wrappers/base_wrapper.py
torchrl/envs/wrappers/misc_wrappers.py
torchrl/envs/wrappers/record_wrappers.py
torchrl/envs/wrappers/reward_wrapper.py
torchrl/envs/wrappers/state_wrapper.py
torchrl/envs/wrappers/stats_recorder.py
torchrl/models/__init__.py
torchrl/models/a2c_model.py
torchrl/models/base_model.py
torchrl/models/base_pg_model.py
torchrl/models/base_pg_model_deprecated.py
torchrl/models/ppo_adaptive_model.py
torchrl/models/ppo_clip_model.py
torchrl/models/ppo_model_deprecated.py
torchrl/models/surrogate_pg_model.py
torchrl/models/surrogate_pg_model_deprecated.py
torchrl/models/value_clip_model.py
torchrl/models/value_model.py
torchrl/models/vanilla_pg_model.py
torchrl/models/vanilla_pg_model_deprecated.py
torchrl/nn/__init__.py
torchrl/nn/container.py
torchrl/optimizers/__init__.py
torchrl/optimizers/base_opt.py
torchrl/optimizers/joint_opt.py
torchrl/optimizers/list_opt.py
torchrl/optimizers/single_opt.py
torchrl/runners/__init__.py
