Metadata-Version: 2.1
Name: reward
Version: 0.0.4
Summary: Reinforcement Learning library
Home-page: https://github.com/lgvaz/reward
Author: lgvaz
Author-email: lucasgouvaz@gmail.com
License: UNKNOWN
Platform: UNKNOWN
